README.md
setup.py
tw_day/__init__.py
tw_day/core.py
tw_day/holiday.py
tw_day/stock_close.py
tw_day/test.py
tw_day.egg-info/PKG-INFO
tw_day.egg-info/SOURCES.txt
tw_day.egg-info/dependency_links.txt
tw_day.egg-info/not-zip-safe
tw_day.egg-info/top_level.txt
tw_day/data/2002.holiday
tw_day/data/2003.holiday
tw_day/data/2004.holiday
tw_day/data/2005.holiday
tw_day/data/2006.holiday
tw_day/data/2007.holiday
tw_day/data/2008.holiday
tw_day/data/2009.holiday
tw_day/data/2010.holiday
tw_day/data/2011.holiday
tw_day/data/2012.holiday
tw_day/data/2013.holiday
tw_day/data/2014.holiday
tw_day/data/2015.holiday
tw_day/data/2016.holiday
tw_day/data/2017.holiday
tw_day/data/2018.holiday