Metadata-Version: 1.0
Name: tw-day
Version: 0.1
Summary: Check if the day is holiday/stock market close day
Home-page: https://github.com/chunpaiyang/tw_day
Author: chunpaiyang
Author-email: chunpaiyang@gmail.com
License: MIT
Platform: UNKNOWN
